st_input_slider/__init__.py
st_input_slider/example.py
st_input_slider/frontend/build/asset-manifest.json
st_input_slider/frontend/build/bootstrap.min.css
st_input_slider/frontend/build/index.html
st_input_slider/frontend/build/static/js/main.220dc884.js
st_input_slider/frontend/build/static/js/main.220dc884.js.LICENSE.txt
st_input_slider/frontend/build/static/js/main.220dc884.js.map
st_input_slider/frontend/build/static/js/main.33814ffc.js
st_input_slider/frontend/build/static/js/main.33814ffc.js.LICENSE.txt
st_input_slider/frontend/build/static/js/main.33814ffc.js.map
st_input_slider/frontend/build/static/js/main.4ba2a0fe.js
st_input_slider/frontend/build/static/js/main.4ba2a0fe.js.LICENSE.txt
st_input_slider/frontend/build/static/js/main.4ba2a0fe.js.map
st_input_slider/frontend/build/static/js/main.9f106bd8.js
st_input_slider/frontend/build/static/js/main.9f106bd8.js.LICENSE.txt
st_input_slider/frontend/build/static/js/main.9f106bd8.js.map
st_input_slider/frontend/build/static/js/main.b432e903.js
st_input_slider/frontend/build/static/js/main.b432e903.js.LICENSE.txt
st_input_slider/frontend/build/static/js/main.b432e903.js.map
st_input_slider/frontend/build/static/js/main.dea17660.js
st_input_slider/frontend/build/static/js/main.dea17660.js.LICENSE.txt
st_input_slider/frontend/build/static/js/main.dea17660.js.map
st_input_slider/frontend/build/static/js/main.f25fcbdb.js
st_input_slider/frontend/build/static/js/main.f25fcbdb.js.LICENSE.txt
st_input_slider/frontend/build/static/js/main.f25fcbdb.js.map
st_input_slider/utils/__init__.py
st_input_slider/utils/callback.py
st_input_slider/utils/component_func.py
st_input_slider/widgets/__init__.py
st_input_slider/widgets/input_slider.py
st_input_slider-0.1.3.dist-info/LICENSE
st_input_slider-0.1.3.dist-info/METADATA
st_input_slider-0.1.3.dist-info/WHEEL
st_input_slider-0.1.3.dist-info/top_level.txt
st_input_slider-0.1.3.dist-info/RECORD
