Metadata-Version: 2.1
Name: st-input-slider
Version: 0.1.3
Summary: A custom Streamlit component that combines a slider with an input box for more precise value selection
Home-page: https://github.com/balexandermunoz/st-input-slider
Author: Brayan Munoz
Author-email: balexander.munoz@udea.edu.co
Requires-Python: >=3.7
License-File: LICENSE
Requires-Dist: streamlit >=0.63
Provides-Extra: devel
Requires-Dist: wheel ; extra == 'devel'
Requires-Dist: pytest ==7.4.0 ; extra == 'devel'
Requires-Dist: playwright ==1.39.0 ; extra == 'devel'
Requires-Dist: requests ==2.31.0 ; extra == 'devel'
Requires-Dist: pytest-playwright-snapshot ==1.0 ; extra == 'devel'
Requires-Dist: pytest-rerunfailures ==12.0 ; extra == 'devel'
